<?xml version="1.0" encoding="UTF-8"?><record_update>
    <x_snc_airop_check_definition action="DELETE">
<ai_justification><![CDATA[Now Assist Virtual Agent integration enables AI-powered intent matching and generative response capabilities within VA conversations.]]></ai_justification>
<check_name>Now Assist VA Integration</check_name>
<check_script><![CDATA[(function(checkDef, dateFilter) {
    var checkPlugin = (function checkPlugin(storeScope, pluginSource) {    var result = { found: false, version: "", table: "" };    try {        var saGR = new GlideRecord("sys_store_app");        saGR.addQuery("scope", storeScope);        saGR.setLimit(1);        saGR.query();        if (saGR.next()) {            result.found = true;            result.version = saGR.getValue("version") || "";            result.table = "sys_store_app";            return result;        }    } catch(e1) {}    if (pluginSource) {        try {            var spGR = new GlideRecord("sys_plugins");            spGR.addQuery("source", pluginSource);            spGR.addQuery("active", true);            spGR.setLimit(1);            spGR.query();            if (spGR.next()) {                result.found = true;                result.version = spGR.getValue("version") || "";                result.table = "sys_plugins";                return result;            }        } catch(e2) {}    }    return result;});
    var result = checkPlugin("sn_nowassist_va", "sn_nowassist_va");
    if (result.found) {
        return {
            status: "ready",
            actualValue: "Now Assist VA Integration (" + "sn_nowassist_va" + ") installed | version: " + result.version + " | source: " + result.table,
            finding: "Now Assist VA integration is installed. Generative AI responses and enhanced intent matching are available in VA conversations."
        };
    } else {
        return {
            status: "not_ready",
            actualValue: "Now Assist VA Integration (sn_nowassist_va) not found in sys_store_app or sys_plugins",
            finding: "Now Assist VA integration (sn_nowassist_va) not found. Generative AI responses and enhanced intent matching are unavailable in VA conversations."
        };
    }
})()]]></check_script>
<is_active>true</is_active>
<is_clone_sensitive>false</is_clone_sensitive>
<is_manual>false</is_manual>
<module>VIRTUAL_AGENT</module>
<number>CHK0006127</number>
<order>20</order>
<remediation_guidance>Activate Now Assist VA plugin (sn_nowassist_va) via sys_plugins_list.do. Configure Now Assist integration in VA Admin Console. Now Assist enhances VA with generative AI and improved intent matching.</remediation_guidance>
<sys_created_by>admin</sys_created_by>
<sys_created_on>2026-06-09 22:05:59</sys_created_on>
<sys_id>8e03e33acfd903108935fb251d851c1a</sys_id>
<sys_mod_count>0</sys_mod_count>
<sys_updated_by>admin</sys_updated_by>
<sys_updated_on>2026-06-09 22:05:59</sys_updated_on>
</x_snc_airop_check_definition>
    <sys_update_version action="INSERT_OR_UPDATE">
        <action>DELETE</action>
        <application/>
        <file_path/>
        <instance_id>48bb485aebdefa90cbdefceacad0cd82</instance_id>
        <instance_name>demoalectriallwf137518</instance_name>
        <name>x_snc_airop_check_definition_8e03e33acfd903108935fb251d851c1a</name>
        <payload>&lt;?xml version="1.0" encoding="UTF-8"?&gt;&lt;record_update&gt;&lt;x_snc_airop_check_definition action="INSERT_OR_UPDATE"&gt;
&lt;ai_justification&gt;&lt;![CDATA[Now Assist Virtual Agent integration enables AI-powered intent matching and generative response capabilities within VA conversations.]]&gt;&lt;/ai_justification&gt;
&lt;check_name&gt;Now Assist VA Integration&lt;/check_name&gt;
&lt;check_script&gt;&lt;![CDATA[(function(checkDef, dateFilter) {
    var checkPlugin = (function checkPlugin(storeScope, pluginSource) {    var result = { found: false, version: "", table: "" };    try {        var saGR = new GlideRecord("sys_store_app");        saGR.addQuery("scope", storeScope);        saGR.setLimit(1);        saGR.query();        if (saGR.next()) {            result.found = true;            result.version = saGR.getValue("version") || "";            result.table = "sys_store_app";            return result;        }    } catch(e1) {}    if (pluginSource) {        try {            var spGR = new GlideRecord("sys_plugins");            spGR.addQuery("source", pluginSource);            spGR.addQuery("active", true);            spGR.setLimit(1);            spGR.query();            if (spGR.next()) {                result.found = true;                result.version = spGR.getValue("version") || "";                result.table = "sys_plugins";                return result;            }        } catch(e2) {}    }    return result;});
    var result = checkPlugin("sn_nowassist_va", "sn_nowassist_va");
    if (result.found) {
        return {
            status: "ready",
            actualValue: "Now Assist VA Integration (" + "sn_nowassist_va" + ") installed | version: " + result.version + " | source: " + result.table,
            finding: "Now Assist VA integration is installed. Generative AI responses and enhanced intent matching are available in VA conversations."
        };
    } else {
        return {
            status: "not_ready",
            actualValue: "Now Assist VA Integration (sn_nowassist_va) not found in sys_store_app or sys_plugins",
            finding: "Now Assist VA integration (sn_nowassist_va) not found. Generative AI responses and enhanced intent matching are unavailable in VA conversations."
        };
    }
})()]]&gt;&lt;/check_script&gt;
&lt;is_active&gt;true&lt;/is_active&gt;
&lt;is_clone_sensitive&gt;false&lt;/is_clone_sensitive&gt;
&lt;is_manual&gt;false&lt;/is_manual&gt;
&lt;module&gt;VIRTUAL_AGENT&lt;/module&gt;
&lt;number&gt;CHK0006127&lt;/number&gt;
&lt;order&gt;20&lt;/order&gt;
&lt;remediation_guidance&gt;Activate Now Assist VA plugin (sn_nowassist_va) via sys_plugins_list.do. Configure Now Assist integration in VA Admin Console. Now Assist enhances VA with generative AI and improved intent matching.&lt;/remediation_guidance&gt;
&lt;sys_created_by&gt;admin&lt;/sys_created_by&gt;
&lt;sys_created_on&gt;2026-06-09 22:05:59&lt;/sys_created_on&gt;
&lt;sys_id&gt;8e03e33acfd903108935fb251d851c1a&lt;/sys_id&gt;
&lt;sys_mod_count&gt;0&lt;/sys_mod_count&gt;
&lt;sys_updated_by&gt;admin&lt;/sys_updated_by&gt;
&lt;sys_updated_on&gt;2026-06-09 22:05:59&lt;/sys_updated_on&gt;
&lt;/x_snc_airop_check_definition&gt;&lt;/record_update&gt;</payload>
        <payload_hash>1591244434</payload_hash>
        <record_name/>
        <reverted_from/>
        <source>1e8ee859cf1183508935fb251d851c20</source>
        <source_table>sys_update_set</source_table>
        <state>current</state>
        <sys_created_by>admin</sys_created_by>
        <sys_created_on>2026-06-10 05:21:25</sys_created_on>
        <sys_id>14b64147cf9947108935fb251d851c2b</sys_id>
        <sys_mod_count>0</sys_mod_count>
        <sys_recorded_at>19eaffa6c4b0000001</sys_recorded_at>
        <sys_updated_by>admin</sys_updated_by>
        <sys_updated_on>2026-06-10 05:21:25</sys_updated_on>
        <type>Check Definition</type>
        <update_guid>50b60147de994710755717e52f8962f8</update_guid>
        <update_guid_history>50b60147de994710755717e52f8962f8:1591244434</update_guid_history>
    </sys_update_version>
    <sys_metadata_delete action="INSERT_OR_UPDATE">
        <sys_audit_delete display_value="">852fcdcfcfdd47108935fb251d851ce3</sys_audit_delete>
        <sys_class_name>sys_metadata_delete</sys_class_name>
        <sys_created_by>admin</sys_created_by>
        <sys_created_on>2026-06-10 05:58:19</sys_created_on>
        <sys_db_object display_value="" name="x_snc_airop_check_definition">x_snc_airop_check_definition</sys_db_object>
        <sys_id>49b1cd549a1c41bf87c8f6868c663c61</sys_id>
        <sys_metadata>8e03e33acfd903108935fb251d851c1a</sys_metadata>
        <sys_mod_count>0</sys_mod_count>
        <sys_name/>
        <sys_package display_value="ServiceNow AI Readiness Optimization Platform" source="x_snc_airop">73e2562fcf244b908935fb251d851c78</sys_package>
        <sys_parent/>
        <sys_policy/>
        <sys_scope display_value="ServiceNow AI Readiness Optimization Platform">73e2562fcf244b908935fb251d851c78</sys_scope>
        <sys_scope_delete display_value="">3d15655892484816825b3e4059b36991</sys_scope_delete>
        <sys_update_name>x_snc_airop_check_definition_8e03e33acfd903108935fb251d851c1a</sys_update_name>
        <sys_update_version display_value="x_snc_airop_check_definition_8e03e33acfd903108935fb251d851c1a">14b64147cf9947108935fb251d851c2b</sys_update_version>
        <sys_updated_by>admin</sys_updated_by>
        <sys_updated_on>2026-06-10 05:58:19</sys_updated_on>
    </sys_metadata_delete>
</record_update>
