<?xml version="1.0" encoding="UTF-8"?><record_update>
    <x_snc_airop_check_definition action="DELETE">
<ai_justification><![CDATA[Benefits realization data enables Now Assist SPM to validate AI portfolio investment recommendations with historical ROI evidence.]]></ai_justification>
<check_name>Benefits Realization Tracking</check_name>
<check_script><![CDATA[(function(checkDef, dateFilter) {
    // pm_project.state is INTEGER: 3=Closed Complete, 4=Closed Incomplete
    // pm_project.state INTEGER: 3=Closed Complete, 4=Closed Incomplete, 7=Closed Skipped
    var gaTotal = new GlideAggregate('pm_project');
    gaTotal.addQuery('state', 'IN', '3,4,7');
    gaTotal.addAggregate('COUNT');
    gaTotal.query();
    var total = gaTotal.next() ? parseInt(gaTotal.getAggregate('COUNT')) : 0;

    if (total === 0) {
        return {
            status: 'not_applicable',
            actualValue: 'No closed projects found',
            finding: 'No closed projects found on this instance. Benefits realization tracking cannot be assessed.'
        };
    }

    var gaWithBenefit = new GlideAggregate('pm_project');
    gaWithBenefit.addQuery('state', 'IN', '3,4,7');
    gaWithBenefit.addQuery('actual_benefit', '>', 0);
    gaWithBenefit.addAggregate('COUNT');
    gaWithBenefit.query();
    var withBenefit = gaWithBenefit.next() ? parseInt(gaWithBenefit.getAggregate('COUNT')) : 0;

    var actualValue = withBenefit + ' of ' + total + ' closed projects with benefits tracked';

    if (withBenefit >= 10) {
        return {
            status: 'ready',
            actualValue: actualValue,
            finding: withBenefit + ' closed projects with benefits data. Now Assist SPM can validate AI portfolio recommendations with historical ROI.'
        };
    } else if (withBenefit >= 3) {
        return {
            status: 'needs_attention',
            actualValue: actualValue,
            finding: 'Only ' + withBenefit + ' closed projects have benefits tracked (target: 10+). Now Assist SPM historical ROI validation will have limited data.'
        };
    } else {
        return {
            status: 'not_ready',
            actualValue: actualValue,
            finding: 'Only ' + withBenefit + ' closed projects have benefits data. Now Assist SPM validates AI portfolio recommendations with historical ROI — insufficient data limits AI accuracy.'
        };
    }
})]]></check_script>
<is_active>true</is_active>
<is_clone_sensitive>false</is_clone_sensitive>
<is_manual>false</is_manual>
<module>SPM</module>
<number>CHK0006100</number>
<order>90</order>
<remediation_guidance>Configure benefits realization tracking on projects. Record actual benefits greater than zero after project completion. Target: 10+ closed projects with benefits data. Now Assist SPM uses this for AI ROI validation.</remediation_guidance>
<sys_created_by>admin</sys_created_by>
<sys_created_on>2026-06-09 22:05:59</sys_created_on>
<sys_id>c203a33acfd903108935fb251d851ccf</sys_id>
<sys_mod_count>0</sys_mod_count>
<sys_updated_by>admin</sys_updated_by>
<sys_updated_on>2026-06-09 22:05:59</sys_updated_on>
</x_snc_airop_check_definition>
    <sys_update_version action="INSERT_OR_UPDATE">
        <action>DELETE</action>
        <application/>
        <file_path/>
        <instance_id>48bb485aebdefa90cbdefceacad0cd82</instance_id>
        <instance_name>demoalectriallwf137518</instance_name>
        <name>x_snc_airop_check_definition_c203a33acfd903108935fb251d851ccf</name>
        <payload>&lt;?xml version="1.0" encoding="UTF-8"?&gt;&lt;record_update&gt;&lt;x_snc_airop_check_definition action="INSERT_OR_UPDATE"&gt;
&lt;ai_justification&gt;&lt;![CDATA[Benefits realization data enables Now Assist SPM to validate AI portfolio investment recommendations with historical ROI evidence.]]&gt;&lt;/ai_justification&gt;
&lt;check_name&gt;Benefits Realization Tracking&lt;/check_name&gt;
&lt;check_script&gt;&lt;![CDATA[(function(checkDef, dateFilter) {
    // pm_project.state is INTEGER: 3=Closed Complete, 4=Closed Incomplete
    // pm_project.state INTEGER: 3=Closed Complete, 4=Closed Incomplete, 7=Closed Skipped
    var gaTotal = new GlideAggregate('pm_project');
    gaTotal.addQuery('state', 'IN', '3,4,7');
    gaTotal.addAggregate('COUNT');
    gaTotal.query();
    var total = gaTotal.next() ? parseInt(gaTotal.getAggregate('COUNT')) : 0;

    if (total === 0) {
        return {
            status: 'not_applicable',
            actualValue: 'No closed projects found',
            finding: 'No closed projects found on this instance. Benefits realization tracking cannot be assessed.'
        };
    }

    var gaWithBenefit = new GlideAggregate('pm_project');
    gaWithBenefit.addQuery('state', 'IN', '3,4,7');
    gaWithBenefit.addQuery('actual_benefit', '&gt;', 0);
    gaWithBenefit.addAggregate('COUNT');
    gaWithBenefit.query();
    var withBenefit = gaWithBenefit.next() ? parseInt(gaWithBenefit.getAggregate('COUNT')) : 0;

    var actualValue = withBenefit + ' of ' + total + ' closed projects with benefits tracked';

    if (withBenefit &gt;= 10) {
        return {
            status: 'ready',
            actualValue: actualValue,
            finding: withBenefit + ' closed projects with benefits data. Now Assist SPM can validate AI portfolio recommendations with historical ROI.'
        };
    } else if (withBenefit &gt;= 3) {
        return {
            status: 'needs_attention',
            actualValue: actualValue,
            finding: 'Only ' + withBenefit + ' closed projects have benefits tracked (target: 10+). Now Assist SPM historical ROI validation will have limited data.'
        };
    } else {
        return {
            status: 'not_ready',
            actualValue: actualValue,
            finding: 'Only ' + withBenefit + ' closed projects have benefits data. Now Assist SPM validates AI portfolio recommendations with historical ROI — insufficient data limits AI accuracy.'
        };
    }
})]]&gt;&lt;/check_script&gt;
&lt;is_active&gt;true&lt;/is_active&gt;
&lt;is_clone_sensitive&gt;false&lt;/is_clone_sensitive&gt;
&lt;is_manual&gt;false&lt;/is_manual&gt;
&lt;module&gt;SPM&lt;/module&gt;
&lt;number&gt;CHK0006100&lt;/number&gt;
&lt;order&gt;90&lt;/order&gt;
&lt;remediation_guidance&gt;Configure benefits realization tracking on projects. Record actual benefits greater than zero after project completion. Target: 10+ closed projects with benefits data. Now Assist SPM uses this for AI ROI validation.&lt;/remediation_guidance&gt;
&lt;sys_created_by&gt;admin&lt;/sys_created_by&gt;
&lt;sys_created_on&gt;2026-06-09 22:05:59&lt;/sys_created_on&gt;
&lt;sys_id&gt;c203a33acfd903108935fb251d851ccf&lt;/sys_id&gt;
&lt;sys_mod_count&gt;0&lt;/sys_mod_count&gt;
&lt;sys_updated_by&gt;admin&lt;/sys_updated_by&gt;
&lt;sys_updated_on&gt;2026-06-09 22:05:59&lt;/sys_updated_on&gt;
&lt;/x_snc_airop_check_definition&gt;&lt;/record_update&gt;</payload>
        <payload_hash>-799679064</payload_hash>
        <record_name/>
        <reverted_from/>
        <source>1e8ee859cf1183508935fb251d851c20</source>
        <source_table>sys_update_set</source_table>
        <state>current</state>
        <sys_created_by>admin</sys_created_by>
        <sys_created_on>2026-06-10 05:21:19</sys_created_on>
        <sys_id>4ba68907cf9947108935fb251d851c0f</sys_id>
        <sys_mod_count>0</sys_mod_count>
        <sys_recorded_at>19eaffa55460000001</sys_recorded_at>
        <sys_updated_by>admin</sys_updated_by>
        <sys_updated_on>2026-06-10 05:21:19</sys_updated_on>
        <type>Check Definition</type>
        <update_guid>b2a689076599471033abb502384e760e</update_guid>
        <update_guid_history>b2a689076599471033abb502384e760e:-799679064</update_guid_history>
    </sys_update_version>
    <sys_metadata_delete action="INSERT_OR_UPDATE">
        <sys_audit_delete display_value="">552f8103cf1187108935fb251d851c1d</sys_audit_delete>
        <sys_class_name>sys_metadata_delete</sys_class_name>
        <sys_created_by>admin</sys_created_by>
        <sys_created_on>2026-06-10 05:58:20</sys_created_on>
        <sys_db_object display_value="" name="x_snc_airop_check_definition">x_snc_airop_check_definition</sys_db_object>
        <sys_id>19d936ef310c494d842036c3e62adb41</sys_id>
        <sys_metadata>c203a33acfd903108935fb251d851ccf</sys_metadata>
        <sys_mod_count>0</sys_mod_count>
        <sys_name/>
        <sys_package display_value="ServiceNow AI Readiness Optimization Platform" source="x_snc_airop">73e2562fcf244b908935fb251d851c78</sys_package>
        <sys_parent/>
        <sys_policy/>
        <sys_scope display_value="ServiceNow AI Readiness Optimization Platform">73e2562fcf244b908935fb251d851c78</sys_scope>
        <sys_scope_delete display_value="">3d15655892484816825b3e4059b36991</sys_scope_delete>
        <sys_update_name>x_snc_airop_check_definition_c203a33acfd903108935fb251d851ccf</sys_update_name>
        <sys_update_version display_value="x_snc_airop_check_definition_c203a33acfd903108935fb251d851ccf">4ba68907cf9947108935fb251d851c0f</sys_update_version>
        <sys_updated_by>admin</sys_updated_by>
        <sys_updated_on>2026-06-10 05:58:20</sys_updated_on>
    </sys_metadata_delete>
</record_update>
